pyjackson/__init__.py
pyjackson/_typing_utils.py
pyjackson/_typing_utils35.py
pyjackson/_typing_utils36.py
pyjackson/_typing_utils37.py
pyjackson/_typing_utils39.py
pyjackson/builtin_types.py
pyjackson/core.py
pyjackson/decorators.py
pyjackson/deserialization.py
pyjackson/errors.py
pyjackson/generics.py
pyjackson/helpers.py
pyjackson/pydantic_ext.py
pyjackson/serialization.py
pyjackson/utils.py
pyjackson-0.0.28.dist-info/AUTHORS.rst
pyjackson-0.0.28.dist-info/LICENSE
pyjackson-0.0.28.dist-info/METADATA
pyjackson-0.0.28.dist-info/WHEEL
pyjackson-0.0.28.dist-info/top_level.txt
pyjackson-0.0.28.dist-info/RECORD
